LICENSE
README.md
lzss.h
lzss0.c
lzss0.cpython-311-x86_64-linux-gnu.so
lzss0.pyx
setup.py
lzss0.egg-info/PKG-INFO
lzss0.egg-info/SOURCES.txt
lzss0.egg-info/dependency_links.txt
lzss0.egg-info/requires.txt
lzss0.egg-info/top_level.txt